mobiwusi/__init__.py
mobiwusi/auth.py
mobiwusi/exceptions.py
mobiwusi/synchronizer.py
mobiwusi/uploader.py
mobiwusi/utils.py
mobiwusi-0.1.6.dist-info/METADATA
mobiwusi-0.1.6.dist-info/WHEEL
mobiwusi-0.1.6.dist-info/RECORD
