Metadata-Version: 2.3
Name: mobiwusi
Version: 0.1.6
Summary: 文件上传与同步工具包
License: MIT
Keywords: upload,sync,file,mobiwusi
Author: mobiwusi
Author-email: app@mobiwusi.com
Requires-Python: >=3.6
Classifier: License :: OSI Approved :: MIT License
Classifier: Programming Language :: Python :: 3
Classifier: Programming Language :: Python :: 3.6
Classifier: Programming Language :: Python :: 3.7
Classifier: Programming Language :: Python :: 3.8
Classifier: Programming Language :: Python :: 3.9
Classifier: Programming Language :: Python :: 3.10
Classifier: Programming Language :: Python :: 3.11
Classifier: Programming Language :: Python :: 3.12
Classifier: Programming Language :: Python :: 3.13
Requires-Dist: pydantic (>=2.0)
Requires-Dist: requests (>=2.20.0)
Project-URL: Documentation, https://github.com/mobiwusi/mobiwusi
Project-URL: Homepage, https://github.com/mobiwusi
Project-URL: Repository, https://github.com/mobiwusi/mobiwusi
